oscpy/__init__.py
oscpy/cli.py
oscpy/client.py
oscpy/parser.py
oscpy/server.py
oscpy/stats.py
oscpy-0.6.0.dist-info/AUTHORS.txt
oscpy-0.6.0.dist-info/LICENSE.txt
oscpy-0.6.0.dist-info/METADATA
oscpy-0.6.0.dist-info/WHEEL
oscpy-0.6.0.dist-info/entry_points.txt
oscpy-0.6.0.dist-info/top_level.txt
oscpy-0.6.0.dist-info/RECORD
