Metadata-Version: 2.1
Name: oscpy
Version: 0.6.0
Summary: A modern and efficient OSC Client/Server implementation
Home-page: https://github.com/kivy/oscpy
Author: Gabriel Pettier
Author-email: gabriel@kivy.org
License: UNKNOWN
Project-URL: Bug Reports, https://github.com/kivy/oscpy/issues
Project-URL: Source, https://github.com/kivy/oscpy
Keywords: OSC network udp
Platform: UNKNOWN
Classifier: Development Status :: 4 - Beta
Classifier: Intended Audience :: Developers
Classifier: Topic :: Multimedia :: Sound/Audio
Classifier: Topic :: Software Development :: Libraries
Classifier: Topic :: System :: Networking
Classifier: License :: OSI Approved :: MIT License
Classifier: Programming Language :: Python :: 2
Classifier: Programming Language :: Python :: 2.7
Classifier: Programming Language :: Python :: 3
Classifier: Programming Language :: Python :: 3.4
Classifier: Programming Language :: Python :: 3.5
Classifier: Programming Language :: Python :: 3.6
Classifier: Programming Language :: Python :: 3.7
Provides-Extra: dev
Provides-Extra: ci
License-File: LICENSE.txt
License-File: AUTHORS.txt
